minid/__init__.py
minid/exc.py
minid/minid.py
minid/version.py
minid/commands/__init__.py
minid/commands/auth.py
minid/commands/formatting.py
minid/commands/main.py
minid/commands/minid_ops.py
tests/__init__.py
tests/conftest.py
tests/test_auth.py
tests/test_client.py
tests/test_commands.py
tests/test_config.py
tests/test_identifier_translation.py
minid-2.0.1.dist-info/LICENSE
minid-2.0.1.dist-info/METADATA
minid-2.0.1.dist-info/WHEEL
minid-2.0.1.dist-info/entry_points.txt
minid-2.0.1.dist-info/top_level.txt
minid-2.0.1.dist-info/RECORD
