Metadata-Version: 2.1
Name: minid
Version: 2.0.1
Summary: FAIR Research Minimum Viable Identifier
Home-page: https://fair-research.org/
Author: FAIR Research Team
Author-email: UNKNOWN
License: Apache 2.0
Platform: UNKNOWN
Classifier: Intended Audience :: Developers
Classifier: Intended Audience :: Science/Research
Classifier: License :: OSI Approved :: Apache Software License
Classifier: Programming Language :: Python :: 3.6
Classifier: Programming Language :: Python :: 3.7
Classifier: Programming Language :: Python :: 3.8
Classifier: Operating System :: POSIX
Requires-Dist: pytz
Requires-Dist: tzlocal (<3.0)
Requires-Dist: click
Requires-Dist: fair-identifiers-client (>=0.5.0)
Requires-Dist: fair-research-login (>=0.2.4)
